sagellm_backend/__init__.py
sagellm_backend/__init__.pyc
sagellm_backend/base.pyc
sagellm_backend/py.typed
sagellm_backend/registry.pyc
sagellm_backend/__pycache__/__init__.cpython-311.pyc
sagellm_backend/__pycache__/base.cpython-311.pyc
sagellm_backend/__pycache__/capability.cpython-311.pyc
sagellm_backend/__pycache__/registry.cpython-311.pyc
sagellm_backend/attention/__init__.py
sagellm_backend/attention/__init__.pyc
sagellm_backend/attention/base.pyc
sagellm_backend/attention/cpu.pyc
sagellm_backend/attention/__pycache__/__init__.cpython-311.pyc
sagellm_backend/attention/__pycache__/base.cpython-311.pyc
sagellm_backend/attention/__pycache__/cpu.cpython-311.pyc
sagellm_backend/kernels/__init__.py
sagellm_backend/kernels/__init__.pyc
sagellm_backend/kernels/activation.pyc
sagellm_backend/kernels/base.pyc
sagellm_backend/kernels/embedding.pyc
sagellm_backend/kernels/linear.pyc
sagellm_backend/kernels/normalization.pyc
sagellm_backend/kernels/__pycache__/__init__.cpython-311.pyc
sagellm_backend/kernels/__pycache__/activation.cpython-311.pyc
sagellm_backend/kernels/__pycache__/base.cpython-311.pyc
sagellm_backend/kernels/__pycache__/embedding.cpython-311.pyc
sagellm_backend/kernels/__pycache__/linear.cpython-311.pyc
sagellm_backend/kernels/__pycache__/normalization.cpython-311.pyc
sagellm_backend/memory/__init__.py
sagellm_backend/memory/__init__.pyc
sagellm_backend/memory/allocator.pyc
sagellm_backend/memory/memory_handle.pyc
sagellm_backend/memory/memory_pool.pyc
sagellm_backend/memory/pin_memory.pyc
sagellm_backend/memory/__pycache__/__init__.cpython-311.pyc
sagellm_backend/memory/__pycache__/allocator.cpython-311.pyc
sagellm_backend/memory/__pycache__/memory_handle.cpython-311.pyc
sagellm_backend/memory/__pycache__/memory_pool.cpython-311.pyc
sagellm_backend/memory/__pycache__/pin_memory.cpython-311.pyc
sagellm_backend/providers/__init__.py
sagellm_backend/providers/__init__.pyc
sagellm_backend/providers/cpu.pyc
sagellm_backend/providers/cuda.pyc
isagellm_backend-0.4.0.10.dist-info/METADATA
isagellm_backend-0.4.0.10.dist-info/WHEEL
isagellm_backend-0.4.0.10.dist-info/entry_points.txt
isagellm_backend-0.4.0.10.dist-info/top_level.txt
isagellm_backend-0.4.0.10.dist-info/RECORD
