Metadata-Version: 2.4
Name: isagellm-backend
Version: 0.4.0.10
Summary: sageLLM backend provider abstraction (CPU/CUDA/Ascend)
Author: IntelliStream Team
License: Proprietary - IntelliStream
Classifier: Development Status :: 3 - Alpha
Classifier: Programming Language :: Python :: 3
Classifier: Programming Language :: Python :: 3.10
Classifier: Programming Language :: Python :: 3.11
Classifier: Programming Language :: Python :: 3.12
Requires-Python: ==3.11.*
Requires-Dist: isagellm-protocol<0.5.0,>=0.4.0.0
Provides-Extra: dev
Requires-Dist: pytest>=7.0.0; extra == "dev"
Requires-Dist: pytest-cov>=4.0.0; extra == "dev"
Requires-Dist: pytest-asyncio>=0.23.0; extra == "dev"
Requires-Dist: ruff>=0.8.0; extra == "dev"
Requires-Dist: mypy>=1.0.0; extra == "dev"
Requires-Dist: bandit[toml]>=1.7.0; extra == "dev"
Requires-Dist: pre-commit>=3.0.0; extra == "dev"
Requires-Dist: psutil>=5.9.0; extra == "dev"
Requires-Dist: isage-pypi-publisher>=0.2.0; extra == "dev"
